{
  "main": {
    "id": "a0020e6b714d436f",
    "type": "split",
    "children": [
      {
        "id": "85a9a8997d608aa9",
        "type": "tabs",
        "children": [
          {
            "id": "62af8eea27127923",
            "type": "leaf",
            "state": {
              "type": "markdown",
              "state": {
                "file": "templates/one_on_one.md",
                "mode": "source",
                "source": false
              },
              "icon": "lucide-file",
              "title": "one_on_one"
            }
          },
          {
            "id": "2d84910b5709856f",
            "type": "leaf",
            "state": {
              "type": "markdown",
              "state": {
                "file": "templates/one_on_one.md",
                "mode": "source",
                "source": false
              },
              "icon": "lucide-file",
              "title": "one_on_one"
            }
          },
          {
            "id": "60a625c4d959aeba",
            "type": "leaf",
            "state": {
              "type": "markdown",
              "state": {
                "file": "templates/one_on_one.md",
                "mode": "source",
                "source": false
              },
              "icon": "lucide-file",
              "title": "one_on_one"
            }
          },
          {
            "id": "fde9a8b9a5b32655",
            "type": "leaf",
            "state": {
              "type": "markdown",
              "state": {
                "file": "templates/zettle_from_link.md",
                "mode": "source",
                "source": false
              },
              "icon": "lucide-file",
              "title": "zettle_from_link"
            }
          },
          {
            "id": "3c9dbb80b8fa430e",
            "type": "leaf",
            "state": {
              "type": "markdown",
              "state": {
                "file": "templates/zettle_from_link.md",
                "mode": "source",
                "source": false
              },
              "icon": "lucide-file",
              "title": "zettle_from_link"
            }
          },
          {
            "id": "6f7d058ddc927b2f",
            "type": "leaf",
            "state": {
              "type": "markdown",
              "state": {
                "file": "templates/one_on_one.md",
                "mode": "source",
                "source": false
              },
              "icon": "lucide-file",
              "title": "one_on_one"
            }
          },
          {
            "id": "990f68551a01001c",
            "type": "leaf",
            "state": {
              "type": "markdown",
              "state": {
                "file": "meetings/one_on_one/laura [2024-11-19].md",
                "mode": "source",
                "source": false
              },
              "icon": "lucide-file",
              "title": "laura [2024-11-19]"
            }
          },
          {
            "id": "f168f56bb944a7a6",
            "type": "leaf",
            "state": {
              "type": "markdown",
              "state": {
                "file": "templates/zettle_from_link.md",
                "mode": "source",
                "source": false
              },
              "icon": "lucide-file",
              "title": "zettle_from_link"
            }
          },
          {
            "id": "cbeb7a888414c629",
            "type": "leaf",
            "state": {
              "type": "markdown",
              "state": {
                "file": "zettlekasten/foo.md",
                "mode": "source",
                "source": false
              },
              "icon": "lucide-file",
              "title": "foo"
            }
          },
          {
            "id": "301dc54e46c70182",
            "type": "leaf",
            "state": {
              "type": "markdown",
              "state": {
                "file": "templates/one_on_one.md",
                "mode": "source",
                "source": false
              },
              "icon": "lucide-file",
              "title": "one_on_one"
            }
          },
          {
            "id": "9c254c8d3f17bd1f",
            "type": "leaf",
            "state": {
              "type": "markdown",
              "state": {
                "file": "meetings/one_on_one/michael [2024-11-28].md",
                "mode": "source",
                "source": false
              },
              "icon": "lucide-file",
              "title": "michael [2024-11-28]"
            }
          }
        ],
        "currentTab": 10
      }
    ],
    "direction": "vertical"
  },
  "left": {
    "id": "898653ca1d09b3bd",
    "type": "split",
    "children": [
      {
        "id": "1fcfaf7c2a6a7641",
        "type": "tabs",
        "children": [
          {
            "id": "35775db2968b4efc",
            "type": "leaf",
            "state": {
              "type": "file-explorer",
              "state": {
                "sortOrder": "alphabetical"
              },
              "icon": "lucide-folder-closed",
              "title": "Files"
            }
          },
          {
            "id": "c6eae940fc7c12a1",
            "type": "leaf",
            "state": {
              "type": "search",
              "state": {
                "query": "",
                "matchingCase": false,
                "explainSearch": false,
                "collapseAll": false,
                "extraContext": false,
                "sortOrder": "alphabetical"
              },
              "icon": "lucide-search",
              "title": "Search"
            }
          }
        ]
      }
    ],
    "direction": "horizontal",
    "width": 300
  },
  "right": {
    "id": "8db2c9f2ba489bb6",
    "type": "split",
    "children": [
      {
        "id": "ce1fbc71f4e787e2",
        "type": "tabs",
        "children": [
          {
            "id": "be368675525fe629",
            "type": "leaf",
            "state": {
              "type": "outgoing-link",
              "state": {
                "file": "ppppp.md",
                "linksCollapsed": false,
                "unlinkedCollapsed": true
              },
              "icon": "links-going-out",
              "title": "Outgoing links from ppppp"
            }
          },
          {
            "id": "1dbf642327ad5114",
            "type": "leaf",
            "state": {
              "type": "tag",
              "state": {
                "sortOrder": "frequency",
                "useHierarchy": true
              },
              "icon": "lucide-tags",
              "title": "Tags"
            }
          },
          {
            "id": "74cfd598692fb158",
            "type": "leaf",
            "state": {
              "type": "backlink",
              "state": {
                "file": "ppppp.md",
                "collapseAll": false,
                "extraContext": false,
                "sortOrder": "alphabetical",
                "showSearch": false,
                "searchQuery": "",
                "backlinkCollapsed": false,
                "unlinkedCollapsed": true
              },
              "icon": "links-coming-in",
              "title": "Backlinks for ppppp"
            }
          }
        ],
        "currentTab": 2
      }
    ],
    "direction": "horizontal",
    "width": 300,
    "collapsed": true
  },
  "left-ribbon": {
    "hiddenItems": {
      "switcher:Open quick switcher": false,
      "graph:Open graph view": false,
      "templates:Insert template": false,
      "command-palette:Open command palette": false,
      "templater-obsidian:Templater": false
    }
  },
  "active": "9c254c8d3f17bd1f",
  "lastOpenFiles": [
    "meetings/one_on_one/michael [2024-11-28].md",
    "templates/one_on_one.md",
    "templates/moc.md",
    "zettlekasten/2024-11-28.md",
    "zettlekasten/Untitled 1.md",
    "zettlekasten/Untitled 2.md",
    "zettlekasten/Untitled.md",
    "zettlekasten/foo.md",
    "templates/zettle_from_link.md",
    "zettlekasten/neuroscience.md",
    "meetings/one_on_one/laura [2024-11-19].md",
    "templates/zettle_from_note.md",
    "zettlekasten/how to configure zettle from links.md",
    "zettlekasten/something.md",
    "zettlekasten/reference api.md",
    "zettlekasten/reference api for quickadd.md",
    "zettlekasten/pencils need to be handled with care.md",
    "zettlekasten/huh.md",
    "scripts/zettle_from_link.js",
    "zettlekasten/michael.md",
    "meetings/one_on_one/michael [2024-11-19].md",
    "zettlekasten/Meeting Notes with James.md",
    "meetings/laura-2024-11-19.md",
    "meetings/one_on_one/person [2024-11-19].md",
    "meetings/one_on_one/b.md",
    "meetings/one_on_one/test [2024-11-19].md",
    "scripts/one_on_one.js",
    "meetings/one_on_one/bar [2024-11-19].md",
    "meetings/one_on_one",
    "meetings",
    "scripts/foo.js",
    "scripts",
    "references",
    "templates",
    "files",
    "zettlekasten"
  ]
}